LICENSE
README.md
setup.cfg
setup.py
drf_eager_fields/__init__.py
drf_eager_fields/serializers.py
drf_eager_fields/views.py
drf_eager_fields.egg-info/PKG-INFO
drf_eager_fields.egg-info/SOURCES.txt
drf_eager_fields.egg-info/dependency_links.txt
drf_eager_fields.egg-info/top_level.txt