Metadata-Version: 2.1
Name: drf-eager-fields
Version: 0.0.3
Summary: Eager load fields dynamically requested for Django REST Framework
Home-page: https://github.com/davideloba/drf-eager-fields.git
Author: Davide Loba
License: MIT
Keywords: eager,dynamic,drf,serializer
Platform: UNKNOWN
Classifier: Development Status :: 3 - Alpha
Classifier: Intended Audience :: Developers
Classifier: Topic :: Software Development :: Build Tools
Classifier: License :: OSI Approved :: MIT License
Classifier: Programming Language :: Python :: 3
License-File: LICENSE
